setup.py
pycsv/__init__.py
pycsv/exceptions.py
pycsv/loader.py
pycsv.egg-info/PKG-INFO
pycsv.egg-info/SOURCES.txt
pycsv.egg-info/dependency_links.txt
pycsv.egg-info/not-zip-safe
pycsv.egg-info/top_level.txt