Metadata-Version: 1.1
Name: pycsv
Version: 0.2.1
Summary: Simple module for reading csv file
Home-page: https://www.github.com/azime/pycsv/
Author: Abderrahim AZIME
Author-email: azime_1@yahoo.fr
License: UNKNOWN
Platform: any
Classifier: Programming Language :: Python :: 2.7
